datamint/__init__.py
datamint/api/__init__.py
datamint/api/base_api.py
datamint/api/client.py
datamint/api/dto/__init__.py
datamint/api/endpoints/__init__.py
datamint/api/endpoints/annotations_api.py
datamint/api/endpoints/annotationsets_api.py
datamint/api/endpoints/channels_api.py
datamint/api/endpoints/datasetsinfo_api.py
datamint/api/endpoints/deploy_model_api.py
datamint/api/endpoints/models_api.py
datamint/api/endpoints/projects_api.py
datamint/api/endpoints/resources_api.py
datamint/api/endpoints/users_api.py
datamint/api/entity_base_api.py
datamint/apihandler/annotation_api_handler.py
datamint/apihandler/api_handler.py
datamint/apihandler/base_api_handler.py
datamint/apihandler/dto/__init__.py
datamint/apihandler/dto/annotation_dto.py
datamint/apihandler/root_api_handler.py
datamint/client_cmd_tools/__init__.py
datamint/client_cmd_tools/datamint_config.py
datamint/client_cmd_tools/datamint_upload.py
datamint/configs.py
datamint/dataset/__init__.py
datamint/dataset/annotation.py
datamint/dataset/base_dataset.py
datamint/dataset/dataset.py
datamint/entities/__init__.py
datamint/entities/annotations/__init__.py
datamint/entities/annotations/annotation.py
datamint/entities/annotations/image_classification.py
datamint/entities/annotations/image_segmentation.py
datamint/entities/annotations/volume_segmentation.py
datamint/entities/base_entity.py
datamint/entities/cache_manager.py
datamint/entities/channel.py
datamint/entities/datasetinfo.py
datamint/entities/deployjob.py
datamint/entities/project.py
datamint/entities/resource.py
datamint/entities/user.py
datamint/examples/__init__.py
datamint/examples/example_projects.py
datamint/exceptions.py
datamint/lightning/__init__.py
datamint/lightning/datamintdatamodule.py
datamint/logging.yaml
datamint/mlflow/__init__.py
datamint/mlflow/artifact/__init__.py
datamint/mlflow/artifact/datamint_artifacts_repo.py
datamint/mlflow/env_utils.py
datamint/mlflow/env_vars.py
datamint/mlflow/flavors/__init__.py
datamint-2.8.9.dist-info/METADATA
datamint-2.8.9.dist-info/WHEEL
datamint-2.8.9.dist-info/entry_points.txt
datamint-2.8.9.dist-info/RECORD
