Metadata-Version: 2.4
Name: datamint
Version: 2.8.9
Summary: A library for interacting with the Datamint API, designed for efficient data management, processing and Deep Learning workflows.
Requires-Python: >=3.10
Classifier: Programming Language :: Python :: 3
Classifier: Programming Language :: Python :: 3.10
Classifier: Programming Language :: Python :: 3.11
Classifier: Programming Language :: Python :: 3.12
Classifier: Programming Language :: Python :: 3.13
Classifier: Programming Language :: Python :: 3.14
Provides-Extra: dev
Provides-Extra: docs
Requires-Dist: Deprecated (>=1.2.0)
Requires-Dist: aiohttp (>=3.0.0,<4.0.0)
Requires-Dist: aioresponses (>=0.7.8,<0.8.0) ; extra == "dev"
Requires-Dist: albumentations (>=2.0.0)
Requires-Dist: backports-strenum ; python_version < "3.11"
Requires-Dist: certifi (>=2025.0.0)
Requires-Dist: httpx
Requires-Dist: humanize (>=4.0.0,<5.0.0)
Requires-Dist: lazy-loader (>=0.3.0)
Requires-Dist: lightning[extra] (>=2.0.0,!=2.5.1,!=2.5.1.post0)
Requires-Dist: matplotlib
Requires-Dist: medimgkit (>=0.11.2)
Requires-Dist: mlflow (>=3.8.1)
Requires-Dist: nest-asyncio (>=1.0.0,<2.0.0)
Requires-Dist: nibabel (>=4.0.0)
Requires-Dist: numpy
Requires-Dist: opencv-python (>=4.0.0)
Requires-Dist: pandas (>=2.0.0)
Requires-Dist: platformdirs (>=4.0.0,<5.0.0)
Requires-Dist: pydantic (>=2.6.4)
Requires-Dist: pydicom (>=3.0.0,<4.0.0)
Requires-Dist: pylibjpeg (>=2.0.0,<3.0.0)
Requires-Dist: pylibjpeg-libjpeg (>=2.0.0,<3.0.0)
Requires-Dist: pytest (>=7.0.0,<8.0.0) ; extra == "dev"
Requires-Dist: pytest-cov (>=4.0.0,<5.0.0) ; extra == "dev"
Requires-Dist: pyyaml (>=5.0.0)
Requires-Dist: requests (>=2.0.0,<3.0.0)
Requires-Dist: responses (>=0.20.0,<0.21.0) ; extra == "dev"
Requires-Dist: respx (>=0.22.0) ; extra == "dev"
Requires-Dist: rich (>=10.0.0)
Requires-Dist: setuptools (>=57.0) ; extra == "docs"
Requires-Dist: sphinx (>=5.0) ; extra == "docs"
Requires-Dist: sphinx-tabs (>=3.0.0) ; extra == "docs"
Requires-Dist: sphinx_rtd_theme (>=2.0.0) ; extra == "docs"
Requires-Dist: torch (>=1.2.0,!=2.3.0)
Requires-Dist: torchvision (>=0.18.0)
Requires-Dist: tqdm (>=4.0.0,<5.0.0)
Requires-Dist: typing_extensions (>=4.0.0)
